libname/ArrowGui.py
libname/__init__.py
ThreeForces-0.0.1.dist-info/METADATA
ThreeForces-0.0.1.dist-info/WHEEL
ThreeForces-0.0.1.dist-info/top_level.txt
ThreeForces-0.0.1.dist-info/RECORD
